simple_header/__init__.py
simple_header/core.py
simple_header/exceptions.py
simple_header/inspect_headers.py
simple_header/data/header_templates.json
simple_header/data/referer_templates.json
simple_header-0.1.2.dist-info/LICENSE
simple_header-0.1.2.dist-info/METADATA
simple_header-0.1.2.dist-info/WHEEL
simple_header-0.1.2.dist-info/top_level.txt
simple_header-0.1.2.dist-info/RECORD
