Metadata-Version: 2.2
Name: simple-header
Version: 0.1.2
Summary: Seamlessly get authentic and ready-to-use browser headers with ease
Home-page: https://github.com/Lennolium/simple-header
Author: Lennart Haack
Author-email: info@lennolium.dev
License: GPL-3.0
Project-URL: Bug Tracker, https://github.com/Lennolium/simple-header/issues
Project-URL: Source, https://github.com/Lennolium/simple-header
Project-URL: Download, https://github.com/Lennolium/simple-header/releases/latest
Project-URL: Documentation, https://github.com/Lennolium/simple-header/README.md
Platform: any
Classifier: Development Status :: 5 - Production/Stable
Classifier: Topic :: Utilities
Classifier: Programming Language :: Python :: 3
Classifier: Programming Language :: Python :: 3.9
Classifier: Programming Language :: Python :: 3 :: Only
Classifier: License :: OSI Approved :: GNU General Public License v3 (GPLv3)
Classifier: Operating System :: OS Independent
Classifier: Operating System :: POSIX :: Linux
Classifier: Operating System :: Unix
Classifier: Operating System :: MacOS
Classifier: Operating System :: Microsoft :: Windows
Classifier: Natural Language :: English
Classifier: Intended Audience :: Developers
Classifier: Intended Audience :: Science/Research
Requires-Python: >=3.9
License-File: LICENSE
Requires-Dist: simple-useragent==0.1.5
Requires-Dist: tldextract==5.1.3
Requires-Dist: validators==0.34.0
